predictit_client/__init__.py
predictit_client/client.py
predictit_client/contract.py
predictit_client/market.py
predictit_client/tests/__init__.py
predictit_client/tests/test_client.py
predictit_client-0.2.dist-info/LICENSE
predictit_client-0.2.dist-info/METADATA
predictit_client-0.2.dist-info/WHEEL
predictit_client-0.2.dist-info/top_level.txt
predictit_client-0.2.dist-info/RECORD
