Metadata-Version: 2.1
Name: predictit-client
Version: 0.2
Summary: Client API wrapper for PredictIt
Home-page: https://github.com/evbarnett/predicit-client
Author: github.com/evbarnett
Author-email: evbarnett@protonmail.com
License: MIT
Platform: UNKNOWN
Requires-Dist: requests
